python_postman/__init__.py
python_postman/parser.py
python_postman/exceptions/__init__.py
python_postman/exceptions/base.py
python_postman/exceptions/file_error.py
python_postman/exceptions/parse_error.py
python_postman/exceptions/schema_error.py
python_postman/exceptions/validation_error.py
python_postman/execution/__init__.py
python_postman/execution/auth_handler.py
python_postman/execution/context.py
python_postman/execution/exceptions.py
python_postman/execution/executor.py
python_postman/execution/extensions.py
python_postman/execution/response.py
python_postman/execution/results.py
python_postman/execution/script_runner.py
python_postman/execution/variable_resolver.py
python_postman/introspection/__init__.py
python_postman/introspection/auth_resolver.py
python_postman/introspection/variable_tracer.py
python_postman/models/__init__.py
python_postman/models/auth.py
python_postman/models/body.py
python_postman/models/collection.py
python_postman/models/collection_info.py
python_postman/models/cookie.py
python_postman/models/event.py
python_postman/models/folder.py
python_postman/models/header.py
python_postman/models/item.py
python_postman/models/request.py
python_postman/models/response.py
python_postman/models/schema.py
python_postman/models/url.py
python_postman/models/variable.py
python_postman/search/__init__.py
python_postman/search/query.py
python_postman/statistics/__init__.py
python_postman/statistics/collector.py
python_postman/types/__init__.py
python_postman/types/auth_types.py
python_postman/types/http_methods.py
python_postman/utils/__init__.py
python_postman/utils/json_parser.py
python_postman/utils/validators.py
python_postman-0.9.0.dist-info/METADATA
python_postman-0.9.0.dist-info/WHEEL
python_postman-0.9.0.dist-info/licenses/LICENSE
python_postman-0.9.0.dist-info/RECORD
