Metadata-Version: 2.4
Name: python-postman
Version: 0.9.0
Summary: A Python library for parsing and working with Postman collection.json files
Project-URL: Homepage, https://github.com/python-postman/python-postman
Project-URL: Repository, https://github.com/python-postman/python-postman
Project-URL: Documentation, https://python-postman.readthedocs.io
Project-URL: Bug Tracker, https://github.com/python-postman/python-postman/issues
Author: Python Postman Contributors
License: MIT
License-File: LICENSE
Keywords: api,collection,http,parser,postman,testing
Classifier: Development Status :: 4 - Beta
Classifier: Intended Audience :: Developers
Classifier: License :: OSI Approved :: MIT License
Classifier: Operating System :: OS Independent
Classifier: Programming Language :: Python :: 3
Classifier: Programming Language :: Python :: 3.8
Classifier: Programming Language :: Python :: 3.9
Classifier: Programming Language :: Python :: 3.10
Classifier: Programming Language :: Python :: 3.11
Classifier: Programming Language :: Python :: 3.12
Classifier: Programming Language :: Python :: 3.13
Classifier: Topic :: Internet :: WWW/HTTP
Classifier: Topic :: Software Development :: Libraries :: Python Modules
Classifier: Topic :: Software Development :: Testing
Requires-Python: >=3.9
Requires-Dist: httpx>=0.28.1
Provides-Extra: dev
Requires-Dist: black>=23.0.0; extra == 'dev'
Requires-Dist: isort>=5.12.0; extra == 'dev'
Requires-Dist: mypy>=1.0.0; extra == 'dev'
Requires-Dist: pytest-asyncio>=0.21.0; extra == 'dev'
Requires-Dist: pytest-cov>=4.0.0; extra == 'dev'
Requires-Dist: pytest>=8.4.2; extra == 'dev'
Provides-Extra: execution
Requires-Dist: python-dotenv>=1.0.0; extra == 'execution'
